fastapi_mongo_base/__init__.py
fastapi_mongo_base/models.py
fastapi_mongo_base/py.typed
fastapi_mongo_base/routes.py
fastapi_mongo_base/schemas.py
fastapi_mongo_base/sql.py
fastapi_mongo_base/tasks.py
fastapi_mongo_base/__pycache__/__init__.cpython-312.pyc
fastapi_mongo_base/__pycache__/models.cpython-312.pyc
fastapi_mongo_base/__pycache__/routes.cpython-312.pyc
fastapi_mongo_base/__pycache__/schemas.cpython-312.pyc
fastapi_mongo_base/__pycache__/tasks.cpython-312.pyc
fastapi_mongo_base/core/__init__.py
fastapi_mongo_base/core/app_factory.py
fastapi_mongo_base/core/config.py
fastapi_mongo_base/core/db.py
fastapi_mongo_base/core/enums.py
fastapi_mongo_base/core/exceptions.py
fastapi_mongo_base/core/__pycache__/__init__.cpython-312.pyc
fastapi_mongo_base/core/__pycache__/app_factory.cpython-312.pyc
fastapi_mongo_base/core/__pycache__/config.cpython-312.pyc
fastapi_mongo_base/core/__pycache__/db.cpython-312.pyc
fastapi_mongo_base/core/__pycache__/exceptions.cpython-312.pyc
fastapi_mongo_base/utils/__init__.py
fastapi_mongo_base/utils/basic.py
fastapi_mongo_base/utils/bsontools.py
fastapi_mongo_base/utils/timezone.py
fastapi_mongo_base/utils/usso_routes.py
fastapi_mongo_base/utils/__pycache__/__init__.cpython-312.pyc
fastapi_mongo_base/utils/__pycache__/basic.cpython-312.pyc
fastapi_mongo_base/utils/__pycache__/bsontools.cpython-312.pyc
fastapi_mongo_base/utils/__pycache__/timezone.cpython-312.pyc
fastapi_mongo_base-1.0.46.dist-info/licenses/LICENSE.txt
fastapi_mongo_base-1.0.46.dist-info/METADATA
fastapi_mongo_base-1.0.46.dist-info/WHEEL
fastapi_mongo_base-1.0.46.dist-info/top_level.txt
fastapi_mongo_base-1.0.46.dist-info/RECORD
