Metadata-Version: 2.4
Name: fastapi-mongo-base
Version: 1.0.46
Summary: A simple boilerplate application, including models and schemas and abstract router, for FastAPI with MongoDB
Author-email: Mahdi Kiani <mahdikiany@gmail.com>
Maintainer-email: Mahdi Kiani <mahdikiany@gmail.com>
License-Expression: MIT
Project-URL: Homepage, https://github.com/mahdikiani/fastapi-mongo-base-app
Project-URL: Bug Reports, https://github.com/mahdikiani/fastapi-mongo-base-app/issues
Project-URL: Funding, https://github.com/mahdikiani/fastapi-mongo-base-app
Project-URL: Say Thanks!, https://saythanks.io/to/mahdikiani
Project-URL: Source, https://github.com/mahdikiani/fastapi-mongo-base-app
Keywords: fastapi,mongodb,beanie
Classifier: Development Status :: 3 - Alpha
Classifier: Intended Audience :: Developers
Classifier: Topic :: Software Development :: Build Tools
Classifier: Programming Language :: Python :: 3
Classifier: Programming Language :: Python :: 3.10
Classifier: Programming Language :: Python :: 3.11
Classifier: Programming Language :: Python :: 3.12
Classifier: Programming Language :: Python :: 3 :: Only
Requires-Python: >=3.10
License-File: LICENSE.txt
Requires-Dist: pydantic>=2.12.3
Requires-Dist: httpx>=0.28.1
Requires-Dist: singleton_package>=0.8.2
Requires-Dist: json-advanced>=0.12.11
Requires-Dist: pytz>=2025.2
Requires-Dist: beanie>=1.30.0
Requires-Dist: fastapi>=0.119.0
Requires-Dist: uvicorn[standard]>=0.38.0
Requires-Dist: uuid6>=2025.0.1
Provides-Extra: usso
Requires-Dist: usso>=0.28.47; extra == "usso"
Provides-Extra: sql
Requires-Dist: sqlalchemy>=2.0.43; extra == "sql"
Provides-Extra: test
Requires-Dist: pytest; extra == "test"
Requires-Dist: pytest-cov; extra == "test"
Requires-Dist: pytest-asyncio; extra == "test"
Requires-Dist: mongomock_motor; extra == "test"
Requires-Dist: coverage; extra == "test"
Dynamic: license-file
